{
  "id": "1.042",
  "url": "https://www.revisor.mn.gov/statutes/cite/1.042",
  "title": "1.042 CONSENT OF STATE.",
  "text": "The consent of the State of Minnesota is given in accordance with the Constitution of the United States, Article I, Section 8, Clause 17, to the acquisition by the United States in any manner of any land or right or interest in land in this state required for sites for customs houses, courthouses, hospitals, sanitariums, post offices, prisons, reformatories, jails, forestry depots, supply houses, or offices, aviation fields or stations, radio stations, military or naval camps, bases, stations, arsenals, depots, terminals, cantonments, storage places, target ranges, or any other military or naval purpose of the United States.\nSo far as jurisdiction, exclusive or partial, in or over any land or place in Minnesota acquired by the United States for any purpose specified in subdivision 1 is accepted by the head or other authorized officer of any department or independent establishment or agency of the United States as provided by the laws of the United States, the jurisdiction is ceded to the United States, subject to the conditions and reservations of subdivision 3. When the premises abut upon the navigable waters of Minnesota, the jurisdiction shall include the underwater lands adjacent to them lying between the line of low-water mark and the bulkhead or pierhead line as now or hereafter established.\nThe right of the state to cause its civil and criminal process to be executed in any ceded land or place is reserved to the state. The state also reserves the right to impose the following taxes:\n(A) an income tax on persons residing in the land or place or receiving income from transactions occurring or services performed there;\n(B) a sales or use tax levied on or measured by sales, receipts from sales, purchases, storage, or use of tangible personal property in the land or place;\n(C) a tax on personal property situated in the land or place, or on the use of personal property by a private individual, association, or corporation there, except personal property owned by the United States or by law exempt from taxation; and\n(D) a tax on the use of real property within the land or place by a private individual, association, or corporation.",
  "repealed": false,
  "rule": {
    "and": [
      {
        "==": [
          {
            "var": "state"
          },
          "Minnesota"
        ]
      },
      {
        "==": [
          {
            "var": "acquisition_purpose"
          },
          "federal"
        ]
      },
      {
        "in": [
          {
            "var": "site_type"
          },
          [
            "customs houses",
            "courthouses",
            "hospitals",
            "sanitariums",
            "post offices",
            "prisons",
            "reformatories",
            "jails",
            "forestry depots",
            "supply houses",
            "offices",
            "aviation fields",
            "stations",
            "radio stations",
            "military camps",
            "naval camps",
            "bases",
            "stations",
            "arsenals",
            "depots",
            "terminals",
            "cantonments",
            "storage places",
            "target ranges",
            "military purpose",
            "naval purpose"
          ]
        ]
      },
      {
        "or": [
          {
            "==": [
              {
                "var": "jurisdiction_type"
              },
              "exclusive"
            ]
          },
          {
            "==": [
              {
                "var": "jurisdiction_type"
              },
              "partial"
            ]
          }
        ]
      },
      {
        "==": [
          {
            "var": "jurisdiction_accepted"
          },
          true
        ]
      }
    ]
  },
  "examples": [
    {
      "state": "Minnesota",
      "acquisition_purpose": "federal",
      "site_type": "courthouses",
      "jurisdiction_type": "exclusive",
      "jurisdiction_accepted": true
    },
    {
      "state": "Minnesota",
      "acquisition_purpose": "federal",
      "site_type": "military camps",
      "jurisdiction_type": "partial",
      "jurisdiction_accepted": true
    },
    {
      "state": "Minnesota",
      "acquisition_purpose": "federal",
      "site_type": "post offices",
      "jurisdiction_type": "exclusive",
      "jurisdiction_accepted": true
    }
  ],
  "variables": [
    "state",
    "acquisition_purpose",
    "site_type",
    "jurisdiction_type",
    "jurisdiction_accepted"
  ],
  "consequences": [
    "Jurisdiction is ceded to the United States with conditions and reservations. State reserves rights to execute civil and criminal processes and impose certain taxes."
  ]
}